archon_bot/__init__.py
archon_bot/__main__.py
archon_bot/bot.py
archon_bot/commands.py
archon_bot/db.py
archon_bot/permissions.py
archon_bot/tournament.py
archon_bot/utils.py
archon_bot-2.10.dist-info/LICENSE
archon_bot-2.10.dist-info/METADATA
archon_bot-2.10.dist-info/WHEEL
archon_bot-2.10.dist-info/entry_points.txt
archon_bot-2.10.dist-info/top_level.txt
archon_bot-2.10.dist-info/RECORD
